<?xml version="1.0" encoding="utf-8"?>
<BrowseNodeLookupResponse xmlns="http://webservices.amazon.com/AWSECommerceService/2013-08-01">
 <OperationRequest>
  <HTTPHeaders>
   <Header Name="UserAgent" Value="Python-urllib/3.5"/>
  </HTTPHeaders>
  <RequestId>
   1606be87-8ea5-4056-97c1-983c22651951
  </RequestId>
  <Arguments>
   <Argument Name="AWSAccessKeyId" Value="AKIAJEGXYAPQ5DFQWHMA"/>
   <Argument Name="AssociateTag" Value="remaura-20"/>
   <Argument Name="BrowseNodeId" Value="3024166011"/>
   <Argument Name="Operation" Value="BrowseNodeLookup"/>
   <Argument Name="Service" Value="AWSECommerceService"/>
   <Argument Name="Timestamp" Value="2017-02-28T20:32:36Z"/>
   <Argument Name="Version" Value="2013-08-01"/>
   <Argument Name="Signature" Value="0HH5PDgLLsTjebCQjX0xh6dMFqSKXZJrH+cA8WEpG/U="/>
  </Arguments>
  <RequestProcessingTime>
   0.001844126
  </RequestProcessingTime>
 </OperationRequest>
 <BrowseNodes>
  <Request>
   <IsValid>
    True
   </IsValid>
   <BrowseNodeLookupRequest>
    <BrowseNodeId>
     3024166011
    </BrowseNodeId>
   </BrowseNodeLookupRequest>
  </Request>
  <BrowseNode>
   <BrowseNodeId>
    3024166011
   </BrowseNodeId>
   <Name>
    Multivitamins
   </Name>
   <Ancestors>
    <BrowseNode>
     <BrowseNodeId>
      2975294011
     </BrowseNodeId>
     <Name>
      Supplements &amp; Vitamins
     </Name>
     <Ancestors>
      <BrowseNode>
       <BrowseNodeId>
        2975276011
       </BrowseNodeId>
       <Name>
        Health Supplies
       </Name>
       <Ancestors>
        <BrowseNode>
         <BrowseNodeId>
          2975241011
         </BrowseNodeId>
         <Name>
          Cats
         </Name>
         <Ancestors>
          <BrowseNode>
           <BrowseNodeId>
            2619534011
           </BrowseNodeId>
           <Name>
            Categories
           </Name>
           <IsCategoryRoot>
            1
           </IsCategoryRoot>
           <Ancestors>
            <BrowseNode>
             <BrowseNodeId>
              2619533011
             </BrowseNodeId>
             <Name>
              Pet Supplies
             </Name>
            </BrowseNode>
           </Ancestors>
          </BrowseNode>
         </Ancestors>
        </BrowseNode>
       </Ancestors>
      </BrowseNode>
     </Ancestors>
    </BrowseNode>
   </Ancestors>
  </BrowseNode>
 </BrowseNodes>
</BrowseNodeLookupResponse>