<?xml version="1.0" ?><BrowseNodeLookupResponse xmlns="http://webservices.amazon.com/AWSECommerceService/2013-08-01"><OperationRequest><HTTPHeaders><Header Name="UserAgent" Value="Python-urllib/3.5"/></HTTPHeaders><RequestId>814f3e17-6f2b-4395-a395-2993cc4a1361</RequestId><Arguments><Argument Name="AWSAccessKeyId" Value="AKIAJEGXYAPQ5DFQWHMA"/><Argument Name="AssociateTag" Value="remaura-20"/><Argument Name="BrowseNodeId" Value="63834"/><Argument Name="Operation" Value="BrowseNodeLookup"/><Argument Name="Service" Value="AWSECommerceService"/><Argument Name="Timestamp" Value="2017-02-28T04:18:04Z"/><Argument Name="Version" Value="2013-08-01"/><Argument Name="Signature" Value="vnyH6uoDC50cXyd3jhsr+gfsYUi2ruwiMQQtqyyoKpY="/></Arguments><RequestProcessingTime>0.001380659</RequestProcessingTime></OperationRequest><BrowseNodes><Request><IsValid>True</IsValid><BrowseNodeLookupRequest><BrowseNodeId>63834</BrowseNodeId></BrowseNodeLookupRequest></Request><BrowseNode><BrowseNodeId>63834</BrowseNodeId><Name>China</Name><Ancestors><BrowseNode><BrowseNodeId>63831</BrowseNodeId><Name>Far East &amp; Asia</Name><Ancestors><BrowseNode><BrowseNodeId>33</BrowseNodeId><Name>World Music</Name><Ancestors><BrowseNode><BrowseNodeId>301668</BrowseNodeId><Name>Styles</Name><IsCategoryRoot>1</IsCategoryRoot><Ancestors><BrowseNode><BrowseNodeId>5174</BrowseNodeId><Name>CDs &amp; Vinyl</Name></BrowseNode></Ancestors></BrowseNode></Ancestors></BrowseNode></Ancestors></BrowseNode></Ancestors></BrowseNode></BrowseNodes></BrowseNodeLookupResponse>