<?xml version="1.0" encoding="utf-8"?>
<BrowseNodeLookupResponse xmlns="http://webservices.amazon.com/AWSECommerceService/2013-08-01">
 <OperationRequest>
  <HTTPHeaders>
   <Header Name="UserAgent" Value="Python-urllib/3.5"/>
  </HTTPHeaders>
  <RequestId>
   2ead379c-8d9e-4110-9299-4d7f3426cde0
  </RequestId>
  <Arguments>
   <Argument Name="AWSAccessKeyId" Value="AKIAJEGXYAPQ5DFQWHMA"/>
   <Argument Name="AssociateTag" Value="remaura-20"/>
   <Argument Name="BrowseNodeId" Value="318079011"/>
   <Argument Name="Operation" Value="BrowseNodeLookup"/>
   <Argument Name="Service" Value="AWSECommerceService"/>
   <Argument Name="Timestamp" Value="2017-02-28T20:06:03Z"/>
   <Argument Name="Version" Value="2013-08-01"/>
   <Argument Name="Signature" Value="CaTpD68oOKFvk/fvPHHDP3gwcddEeg6D2bTM/5zW9KI="/>
  </Arguments>
  <RequestProcessingTime>
   0.008542601
  </RequestProcessingTime>
 </OperationRequest>
 <BrowseNodes>
  <Request>
   <IsValid>
    True
   </IsValid>
   <BrowseNodeLookupRequest>
    <BrowseNodeId>
     318079011
    </BrowseNodeId>
   </BrowseNodeLookupRequest>
  </Request>
  <BrowseNode>
   <BrowseNodeId>
    318079011
   </BrowseNodeId>
   <Name>
    Lab Filters
   </Name>
   <Children>
    <BrowseNode>
     <BrowseNodeId>
      393363011
     </BrowseNodeId>
     <Name>
      Air Sampling Filters
     </Name>
    </BrowseNode>
    <BrowseNode>
     <BrowseNodeId>
      318080011
     </BrowseNodeId>
     <Name>
      Bottletop Filters
     </Name>
    </BrowseNode>
    <BrowseNode>
     <BrowseNodeId>
      318081011
     </BrowseNodeId>
     <Name>
      Centrifugal Filters
     </Name>
    </BrowseNode>
    <BrowseNode>
     <BrowseNodeId>
      393366011
     </BrowseNodeId>
     <Name>
      Filter Membrane
     </Name>
    </BrowseNode>
    <BrowseNode>
     <BrowseNodeId>
      393367011
     </BrowseNodeId>
     <Name>
      Glass Fiber Filters
     </Name>
    </BrowseNode>
    <BrowseNode>
     <BrowseNodeId>
      393364011
     </BrowseNodeId>
     <Name>
      Inline Filters
     </Name>
    </BrowseNode>
    <BrowseNode>
     <BrowseNodeId>
      393368011
     </BrowseNodeId>
     <Name>
      Qualitative Filter Paper
     </Name>
    </BrowseNode>
    <BrowseNode>
     <BrowseNodeId>
      393369011
     </BrowseNodeId>
     <Name>
      Quantitative Filter Paper
     </Name>
    </BrowseNode>
    <BrowseNode>
     <BrowseNodeId>
      318082011
     </BrowseNodeId>
     <Name>
      Syringe Filters
     </Name>
    </BrowseNode>
    <BrowseNode>
     <BrowseNodeId>
      393370011
     </BrowseNodeId>
     <Name>
      Ultrafiltration Filters
     </Name>
    </BrowseNode>
   </Children>
   <Ancestors>
    <BrowseNode>
     <BrowseNodeId>
      3061625011
     </BrowseNodeId>
     <Name>
      Filtration
     </Name>
     <Ancestors>
      <BrowseNode>
       <BrowseNodeId>
        16310161
       </BrowseNodeId>
       <Name>
        Categories
       </Name>
       <IsCategoryRoot>
        1
       </IsCategoryRoot>
       <Ancestors>
        <BrowseNode>
         <BrowseNodeId>
          16310091
         </BrowseNodeId>
         <Name>
          Industrial &amp; Scientific
         </Name>
        </BrowseNode>
       </Ancestors>
      </BrowseNode>
     </Ancestors>
    </BrowseNode>
   </Ancestors>
  </BrowseNode>
 </BrowseNodes>
</BrowseNodeLookupResponse>