<?xml version="1.0" encoding="utf-8"?>
<BrowseNodeLookupResponse xmlns="http://webservices.amazon.com/AWSECommerceService/2013-08-01">
 <OperationRequest>
  <HTTPHeaders>
   <Header Name="UserAgent" Value="Python-urllib/3.5"/>
  </HTTPHeaders>
  <RequestId>
   359d1543-f046-42ce-a42d-7c1c7edf71ae
  </RequestId>
  <Arguments>
   <Argument Name="AWSAccessKeyId" Value="AKIAJEGXYAPQ5DFQWHMA"/>
   <Argument Name="AssociateTag" Value="remaura-20"/>
   <Argument Name="BrowseNodeId" Value="331553011"/>
   <Argument Name="Operation" Value="BrowseNodeLookup"/>
   <Argument Name="Service" Value="AWSECommerceService"/>
   <Argument Name="Timestamp" Value="2017-02-28T19:57:02Z"/>
   <Argument Name="Version" Value="2013-08-01"/>
   <Argument Name="Signature" Value="Afu/hzn2Xb3txCMh8/TD3Z9rn6vqjXl0O8Zwp8yc638="/>
  </Arguments>
  <RequestProcessingTime>
   0.005840894
  </RequestProcessingTime>
 </OperationRequest>
 <BrowseNodes>
  <Request>
   <IsValid>
    True
   </IsValid>
   <BrowseNodeLookupRequest>
    <BrowseNodeId>
     331553011
    </BrowseNodeId>
   </BrowseNodeLookupRequest>
  </Request>
  <BrowseNode>
   <BrowseNodeId>
    331553011
   </BrowseNodeId>
   <Name>
    Internal Grooving Inserts
   </Name>
   <Ancestors>
    <BrowseNode>
     <BrowseNodeId>
      257523011
     </BrowseNodeId>
     <Name>
      Grooving Inserts
     </Name>
     <Ancestors>
      <BrowseNode>
       <BrowseNodeId>
        257519011
       </BrowseNodeId>
       <Name>
        Indexable Inserts
       </Name>
       <Ancestors>
        <BrowseNode>
         <BrowseNodeId>
          383598011
         </BrowseNodeId>
         <Name>
          Cutting Tools
         </Name>
         <Ancestors>
          <BrowseNode>
           <BrowseNodeId>
            16310161
           </BrowseNodeId>
           <Name>
            Categories
           </Name>
           <IsCategoryRoot>
            1
           </IsCategoryRoot>
           <Ancestors>
            <BrowseNode>
             <BrowseNodeId>
              16310091
             </BrowseNodeId>
             <Name>
              Industrial &amp; Scientific
             </Name>
            </BrowseNode>
           </Ancestors>
          </BrowseNode>
         </Ancestors>
        </BrowseNode>
       </Ancestors>
      </BrowseNode>
     </Ancestors>
    </BrowseNode>
   </Ancestors>
  </BrowseNode>
 </BrowseNodes>
</BrowseNodeLookupResponse>