<?xml version="1.0" ?><BrowseNodeLookupResponse xmlns="http://webservices.amazon.com/AWSECommerceService/2013-08-01"><OperationRequest><HTTPHeaders><Header Name="UserAgent" Value="Python-urllib/3.5"/></HTTPHeaders><RequestId>6709eafc-4582-4228-85d4-38741636f29d</RequestId><Arguments><Argument Name="AWSAccessKeyId" Value="AKIAJEGXYAPQ5DFQWHMA"/><Argument Name="AssociateTag" Value="remaura-20"/><Argument Name="BrowseNodeId" Value="262646011"/><Argument Name="Operation" Value="BrowseNodeLookup"/><Argument Name="Service" Value="AWSECommerceService"/><Argument Name="Timestamp" Value="2017-02-27T22:15:44Z"/><Argument Name="Version" Value="2013-08-01"/><Argument Name="Signature" Value="H7jM5MGH6PmNraA15h73DJjcBfs3TNrztRZTUu3/VnM="/></Arguments><RequestProcessingTime>0.001935483</RequestProcessingTime></OperationRequest><BrowseNodes><Request><IsValid>True</IsValid><BrowseNodeLookupRequest><BrowseNodeId>262646011</BrowseNodeId></BrowseNodeLookupRequest></Request><BrowseNode><BrowseNodeId>262646011</BrowseNodeId><Name>Hoops</Name><Ancestors><BrowseNode><BrowseNodeId>12897321</BrowseNodeId><Name>Quilting</Name><Ancestors><BrowseNode><BrowseNodeId>12899091</BrowseNodeId><Name>Sewing</Name><Ancestors><BrowseNode><BrowseNodeId>2617942011</BrowseNodeId><Name>Categories</Name><IsCategoryRoot>1</IsCategoryRoot><Ancestors><BrowseNode><BrowseNodeId>2617941011</BrowseNodeId><Name>Arts, Crafts &amp; Sewing</Name></BrowseNode></Ancestors></BrowseNode></Ancestors></BrowseNode></Ancestors></BrowseNode></Ancestors></BrowseNode></BrowseNodes></BrowseNodeLookupResponse>