<?xml version="1.0" ?><BrowseNodeLookupResponse xmlns="http://webservices.amazon.com/AWSECommerceService/2013-08-01"><OperationRequest><HTTPHeaders><Header Name="UserAgent" Value="Python-urllib/3.5"/></HTTPHeaders><RequestId>43707699-4113-45d6-b64d-e0e9e034f85b</RequestId><Arguments><Argument Name="AWSAccessKeyId" Value="AKIAJEGXYAPQ5DFQWHMA"/><Argument Name="AssociateTag" Value="remaura-20"/><Argument Name="BrowseNodeId" Value="2478443011"/><Argument Name="Operation" Value="BrowseNodeLookup"/><Argument Name="Service" Value="AWSECommerceService"/><Argument Name="Timestamp" Value="2017-02-28T05:25:16Z"/><Argument Name="Version" Value="2013-08-01"/><Argument Name="Signature" Value="JB0exXttvfyhHnZGMOxmqpdyIhc7s7j3qI+NmboXP5E="/></Arguments><RequestProcessingTime>0.00131611</RequestProcessingTime></OperationRequest><BrowseNodes><Request><IsValid>True</IsValid><BrowseNodeLookupRequest><BrowseNodeId>2478443011</BrowseNodeId></BrowseNodeLookupRequest></Request><BrowseNode><BrowseNodeId>2478443011</BrowseNodeId><Name>Gloves &amp; Mittens</Name><Ancestors><BrowseNode><BrowseNodeId>2478436011</BrowseNodeId><Name>Accessories</Name><Ancestors><BrowseNode><BrowseNodeId>7628013011</BrowseNodeId><Name>Baby Boys</Name><Ancestors><BrowseNode><BrowseNodeId>7147444011</BrowseNodeId><Name>Baby</Name><Ancestors><BrowseNode><BrowseNodeId>7141124011</BrowseNodeId><Name>Departments</Name><IsCategoryRoot>1</IsCategoryRoot><Ancestors><BrowseNode><BrowseNodeId>7141123011</BrowseNodeId><Name>Clothing, Shoes &amp; Jewelry</Name></BrowseNode></Ancestors></BrowseNode></Ancestors></BrowseNode></Ancestors></BrowseNode></Ancestors></BrowseNode></Ancestors></BrowseNode></BrowseNodes></BrowseNodeLookupResponse>