<?xml version="1.0" ?><BrowseNodeLookupResponse xmlns="http://webservices.amazon.com/AWSECommerceService/2013-08-01"><OperationRequest><HTTPHeaders><Header Name="UserAgent" Value="Python-urllib/3.5"/></HTTPHeaders><RequestId>d20bf353-9142-4944-ae38-72b287952431</RequestId><Arguments><Argument Name="AWSAccessKeyId" Value="AKIAJEGXYAPQ5DFQWHMA"/><Argument Name="AssociateTag" Value="remaura-20"/><Argument Name="BrowseNodeId" Value="6114096011"/><Argument Name="Operation" Value="BrowseNodeLookup"/><Argument Name="Service" Value="AWSECommerceService"/><Argument Name="Timestamp" Value="2017-02-28T04:46:37Z"/><Argument Name="Version" Value="2013-08-01"/><Argument Name="Signature" Value="JHVIkpRg+5F8PxlGABfOm9ASzZDN85chDDD0MHmBgvw="/></Arguments><RequestProcessingTime>0.0079541</RequestProcessingTime></OperationRequest><BrowseNodes><Request><IsValid>True</IsValid><BrowseNodeLookupRequest><BrowseNodeId>6114096011</BrowseNodeId></BrowseNodeLookupRequest></Request><BrowseNode><BrowseNodeId>6114096011</BrowseNodeId><Name>Slipper Socks</Name><Ancestors><BrowseNode><BrowseNodeId>6114090011</BrowseNodeId><Name>Socks &amp; Hosiery</Name><Ancestors><BrowseNode><BrowseNodeId>7581676011</BrowseNodeId><Name>Petite</Name><Ancestors><BrowseNode><BrowseNodeId>7581668011</BrowseNodeId><Name>Shops</Name><Ancestors><BrowseNode><BrowseNodeId>7147440011</BrowseNodeId><Name>Women</Name><Ancestors><BrowseNode><BrowseNodeId>7141124011</BrowseNodeId><Name>Departments</Name><IsCategoryRoot>1</IsCategoryRoot><Ancestors><BrowseNode><BrowseNodeId>7141123011</BrowseNodeId><Name>Clothing, Shoes &amp; Jewelry</Name></BrowseNode></Ancestors></BrowseNode></Ancestors></BrowseNode></Ancestors></BrowseNode></Ancestors></BrowseNode></Ancestors></BrowseNode></Ancestors></BrowseNode></BrowseNodes></BrowseNodeLookupResponse>