<?xml version="1.0" ?><BrowseNodeLookupResponse xmlns="http://webservices.amazon.com/AWSECommerceService/2013-08-01"><OperationRequest><HTTPHeaders><Header Name="UserAgent" Value="Python-urllib/3.5"/></HTTPHeaders><RequestId>973f8300-6680-4262-9b7a-d4926e929996</RequestId><Arguments><Argument Name="AWSAccessKeyId" Value="AKIAJEGXYAPQ5DFQWHMA"/><Argument Name="AssociateTag" Value="remaura-20"/><Argument Name="BrowseNodeId" Value="10704397011"/><Argument Name="Operation" Value="BrowseNodeLookup"/><Argument Name="Service" Value="AWSECommerceService"/><Argument Name="Timestamp" Value="2017-02-28T00:06:18Z"/><Argument Name="Version" Value="2013-08-01"/><Argument Name="Signature" Value="Lk5pvbkaBAM6GQU3Mz9hGRMQIjoa/zQeE9mvxF2/+bI="/></Arguments><RequestProcessingTime>0.009345074</RequestProcessingTime></OperationRequest><BrowseNodes><Request><IsValid>True</IsValid><BrowseNodeLookupRequest><BrowseNodeId>10704397011</BrowseNodeId></BrowseNodeLookupRequest></Request><BrowseNode><BrowseNodeId>10704397011</BrowseNodeId><Name>Torches</Name><Ancestors><BrowseNode><BrowseNodeId>13400571</BrowseNodeId><Name>Gas Welding Equipment</Name><Ancestors><BrowseNode><BrowseNodeId>304788011</BrowseNodeId><Name>Welding Equipment &amp; Accessories</Name><Ancestors><BrowseNode><BrowseNodeId>13400481</BrowseNodeId><Name>Welding Equipment</Name><Ancestors><BrowseNode><BrowseNodeId>8106310011</BrowseNodeId><Name>Welding &amp; Soldering</Name><Ancestors><BrowseNode><BrowseNodeId>468240</BrowseNodeId><Name>Categories</Name><IsCategoryRoot>1</IsCategoryRoot><Ancestors><BrowseNode><BrowseNodeId>228013</BrowseNodeId><Name>Tools &amp; Home Improvement</Name></BrowseNode></Ancestors></BrowseNode></Ancestors></BrowseNode></Ancestors></BrowseNode></Ancestors></BrowseNode></Ancestors></BrowseNode></Ancestors></BrowseNode></BrowseNodes></BrowseNodeLookupResponse>