<?xml version="1.0" ?><BrowseNodeLookupResponse xmlns="http://webservices.amazon.com/AWSECommerceService/2013-08-01"><OperationRequest><HTTPHeaders><Header Name="UserAgent" Value="Python-urllib/3.5"/></HTTPHeaders><RequestId>44ea39d3-6a6b-4650-bf02-c7d833719a61</RequestId><Arguments><Argument Name="AWSAccessKeyId" Value="AKIAJEGXYAPQ5DFQWHMA"/><Argument Name="AssociateTag" Value="remaura-20"/><Argument Name="BrowseNodeId" Value="15708921"/><Argument Name="Operation" Value="BrowseNodeLookup"/><Argument Name="Service" Value="AWSECommerceService"/><Argument Name="Timestamp" Value="2017-02-28T00:04:50Z"/><Argument Name="Version" Value="2013-08-01"/><Argument Name="Signature" Value="Ejzk8PDrYYebmgE9Fundy+kAl088OmP0I/MZrAsY+V8="/></Arguments><RequestProcessingTime>0.001849226</RequestProcessingTime></OperationRequest><BrowseNodes><Request><IsValid>True</IsValid><BrowseNodeLookupRequest><BrowseNodeId>15708921</BrowseNodeId></BrowseNodeLookupRequest></Request><BrowseNode><BrowseNodeId>15708921</BrowseNodeId><Name>Spark Plug &amp; Ignition Tools</Name><Ancestors><BrowseNode><BrowseNodeId>15706941</BrowseNodeId><Name>Tools &amp; Equipment</Name><Ancestors><BrowseNode><BrowseNodeId>15690151</BrowseNodeId><Name>Categories</Name><IsCategoryRoot>1</IsCategoryRoot><Ancestors><BrowseNode><BrowseNodeId>15684181</BrowseNodeId><Name>Automotive</Name></BrowseNode></Ancestors></BrowseNode></Ancestors></BrowseNode></Ancestors></BrowseNode></BrowseNodes></BrowseNodeLookupResponse>