<?xml version="1.0" ?><BrowseNodeLookupResponse xmlns="http://webservices.amazon.com/AWSECommerceService/2013-08-01"><OperationRequest><HTTPHeaders><Header Name="UserAgent" Value="Python-urllib/3.5"/></HTTPHeaders><RequestId>a1de09fa-486e-4e68-89f4-7f954f58d43c</RequestId><Arguments><Argument Name="AWSAccessKeyId" Value="AKIAJEGXYAPQ5DFQWHMA"/><Argument Name="AssociateTag" Value="remaura-20"/><Argument Name="BrowseNodeId" Value="15718991"/><Argument Name="Operation" Value="BrowseNodeLookup"/><Argument Name="Service" Value="AWSECommerceService"/><Argument Name="Timestamp" Value="2017-02-27T22:48:08Z"/><Argument Name="Version" Value="2013-08-01"/><Argument Name="Signature" Value="l9J7DMBTLPTvod6B8DhzUgRQtn+IppfoyQ8goM/Qug4="/></Arguments><RequestProcessingTime>0.002306271</RequestProcessingTime></OperationRequest><BrowseNodes><Request><IsValid>True</IsValid><BrowseNodeLookupRequest><BrowseNodeId>15718991</BrowseNodeId></BrowseNodeLookupRequest></Request><BrowseNode><BrowseNodeId>15718991</BrowseNodeId><Name>Carburetor &amp; Throttle Body Cleaners</Name><Ancestors><BrowseNode><BrowseNodeId>15718971</BrowseNodeId><Name>Cleaners</Name><Ancestors><BrowseNode><BrowseNodeId>15718791</BrowseNodeId><Name>Oils &amp; Fluids</Name><Ancestors><BrowseNode><BrowseNodeId>15690151</BrowseNodeId><Name>Categories</Name><IsCategoryRoot>1</IsCategoryRoot><Ancestors><BrowseNode><BrowseNodeId>15684181</BrowseNodeId><Name>Automotive</Name></BrowseNode></Ancestors></BrowseNode></Ancestors></BrowseNode></Ancestors></BrowseNode></Ancestors></BrowseNode></BrowseNodes></BrowseNodeLookupResponse>