<?xml version="1.0" ?><BrowseNodeLookupResponse xmlns="http://webservices.amazon.com/AWSECommerceService/2013-08-01"><OperationRequest><HTTPHeaders><Header Name="UserAgent" Value="Python-urllib/3.5"/></HTTPHeaders><RequestId>11717f7b-e225-4eb4-8637-5f8d97e13089</RequestId><Arguments><Argument Name="AWSAccessKeyId" Value="AKIAJEGXYAPQ5DFQWHMA"/><Argument Name="AssociateTag" Value="remaura-20"/><Argument Name="BrowseNodeId" Value="15726871"/><Argument Name="Operation" Value="BrowseNodeLookup"/><Argument Name="Service" Value="AWSECommerceService"/><Argument Name="Timestamp" Value="2017-02-27T23:28:14Z"/><Argument Name="Version" Value="2013-08-01"/><Argument Name="Signature" Value="+yd2VfFmbXrNTJZx7YuEUxZMfugZfp/Zr53ahbQTeTc="/></Arguments><RequestProcessingTime>0.001402475</RequestProcessingTime></OperationRequest><BrowseNodes><Request><IsValid>True</IsValid><BrowseNodeLookupRequest><BrowseNodeId>15726871</BrowseNodeId></BrowseNodeLookupRequest></Request><BrowseNode><BrowseNodeId>15726871</BrowseNodeId><Name>Hangers</Name><Ancestors><BrowseNode><BrowseNodeId>15726831</BrowseNodeId><Name>Hangers, Clamps &amp; Flanges</Name><Ancestors><BrowseNode><BrowseNodeId>2286887011</BrowseNodeId><Name>Exhaust &amp; Emissions</Name><Ancestors><BrowseNode><BrowseNodeId>15719731</BrowseNodeId><Name>Replacement Parts</Name><Ancestors><BrowseNode><BrowseNodeId>15690151</BrowseNodeId><Name>Categories</Name><IsCategoryRoot>1</IsCategoryRoot><Ancestors><BrowseNode><BrowseNodeId>15684181</BrowseNodeId><Name>Automotive</Name></BrowseNode></Ancestors></BrowseNode></Ancestors></BrowseNode></Ancestors></BrowseNode></Ancestors></BrowseNode></Ancestors></BrowseNode></BrowseNodes></BrowseNodeLookupResponse>