<?xml version="1.0" ?><BrowseNodeLookupResponse xmlns="http://webservices.amazon.com/AWSECommerceService/2013-08-01"><OperationRequest><HTTPHeaders><Header Name="UserAgent" Value="Python-urllib/3.5"/></HTTPHeaders><RequestId>3bf5ba25-a616-474d-94f5-1b4ec0c3b2b0</RequestId><Arguments><Argument Name="AWSAccessKeyId" Value="AKIAJEGXYAPQ5DFQWHMA"/><Argument Name="AssociateTag" Value="remaura-20"/><Argument Name="BrowseNodeId" Value="979833011"/><Argument Name="Operation" Value="BrowseNodeLookup"/><Argument Name="Service" Value="AWSECommerceService"/><Argument Name="Timestamp" Value="2017-02-27T21:12:43Z"/><Argument Name="Version" Value="2013-08-01"/><Argument Name="Signature" Value="cFqFQpsLZUMHcTlGWa38xGxoO8Mb46cbjUd5obe+INw="/></Arguments><RequestProcessingTime>0.001708577</RequestProcessingTime></OperationRequest><BrowseNodes><Request><IsValid>True</IsValid><BrowseNodeLookupRequest><BrowseNodeId>979833011</BrowseNodeId></BrowseNodeLookupRequest></Request><BrowseNode><BrowseNodeId>979833011</BrowseNodeId><Name>Beer Brewing</Name><Children><BrowseNode><BrowseNodeId>979834011</BrowseNodeId><Name>Bottles &amp; Bottling</Name></BrowseNode><BrowseNode><BrowseNodeId>979835011</BrowseNodeId><Name>Brew Pots, Kettles &amp; Accessories</Name></BrowseNode><BrowseNode><BrowseNodeId>979836011</BrowseNodeId><Name>Burners</Name></BrowseNode><BrowseNode><BrowseNodeId>979837011</BrowseNodeId><Name>Filters &amp; Straining</Name></BrowseNode><BrowseNode><BrowseNodeId>979838011</BrowseNodeId><Name>Grain Mills</Name></BrowseNode><BrowseNode><BrowseNodeId>979839011</BrowseNodeId><Name>Home Brewing Starter Sets</Name></BrowseNode><BrowseNode><BrowseNodeId>979840011</BrowseNodeId><Name>Kegs &amp; Kegging</Name></BrowseNode><BrowseNode><BrowseNodeId>979842011</BrowseNodeId><Name>Stirring &amp; Utensils</Name></BrowseNode><BrowseNode><BrowseNodeId>979843011</BrowseNodeId><Name>Wort Chillers</Name></BrowseNode></Children><Ancestors><BrowseNode><BrowseNodeId>979832011</BrowseNodeId><Name>Home Brewing &amp; Wine Making</Name><Ancestors><BrowseNode><BrowseNodeId>284507</BrowseNodeId><Name>Kitchen &amp; Dining</Name><Ancestors><BrowseNode><BrowseNodeId>1063498</BrowseNodeId><Name>Categories</Name><IsCategoryRoot>1</IsCategoryRoot><Ancestors><BrowseNode><BrowseNodeId>1055398</BrowseNodeId><Name>Home &amp; Kitchen</Name></BrowseNode></Ancestors></BrowseNode></Ancestors></BrowseNode></Ancestors></BrowseNode></Ancestors></BrowseNode></BrowseNodes></BrowseNodeLookupResponse>