<?xml version="1.0" ?><BrowseNodeLookupResponse xmlns="http://webservices.amazon.com/AWSECommerceService/2013-08-01"><OperationRequest><HTTPHeaders><Header Name="UserAgent" Value="Python-urllib/3.5"/></HTTPHeaders><RequestId>c536e15c-3fe1-44d5-88ed-f81d4c33e67a</RequestId><Arguments><Argument Name="AWSAccessKeyId" Value="AKIAJEGXYAPQ5DFQWHMA"/><Argument Name="AssociateTag" Value="remaura-20"/><Argument Name="BrowseNodeId" Value="15239990011"/><Argument Name="Operation" Value="BrowseNodeLookup"/><Argument Name="Service" Value="AWSECommerceService"/><Argument Name="Timestamp" Value="2017-02-28T00:41:28Z"/><Argument Name="Version" Value="2013-08-01"/><Argument Name="Signature" Value="M2IoKPa4XIaah7I7KDdcZEDHVV6M4BDlb1C+2w9hXZo="/></Arguments><RequestProcessingTime>0.001265547</RequestProcessingTime></OperationRequest><BrowseNodes><Request><IsValid>True</IsValid><BrowseNodeLookupRequest><BrowseNodeId>15239990011</BrowseNodeId></BrowseNodeLookupRequest></Request><BrowseNode><BrowseNodeId>15239990011</BrowseNodeId><Name>Body Sunscreens</Name><Ancestors><BrowseNode><BrowseNodeId>11062651</BrowseNodeId><Name>Sunscreens</Name><Ancestors><BrowseNode><BrowseNodeId>11062591</BrowseNodeId><Name>Sunscreens &amp; Tanning Products</Name><Ancestors><BrowseNode><BrowseNodeId>11060451</BrowseNodeId><Name>Skin Care</Name><Ancestors><BrowseNode><BrowseNodeId>11055981</BrowseNodeId><Name>Products</Name><IsCategoryRoot>1</IsCategoryRoot><Ancestors><BrowseNode><BrowseNodeId>3760911</BrowseNodeId><Name>Beauty &amp; Personal Care</Name></BrowseNode></Ancestors></BrowseNode></Ancestors></BrowseNode></Ancestors></BrowseNode></Ancestors></BrowseNode></Ancestors></BrowseNode></BrowseNodes></BrowseNodeLookupResponse>