<?xml version="1.0" encoding="utf-8"?>
<BrowseNodeLookupResponse xmlns="http://webservices.amazon.com/AWSECommerceService/2013-08-01">
 <OperationRequest>
  <HTTPHeaders>
   <Header Name="UserAgent" Value="Python-urllib/3.5"/>
  </HTTPHeaders>
  <RequestId>
   fb7ee362-8f14-4dd0-8747-3c6956df573f
  </RequestId>
  <Arguments>
   <Argument Name="AWSAccessKeyId" Value="AKIAJEGXYAPQ5DFQWHMA"/>
   <Argument Name="AssociateTag" Value="remaura-20"/>
   <Argument Name="BrowseNodeId" Value="13336081"/>
   <Argument Name="Operation" Value="BrowseNodeLookup"/>
   <Argument Name="Service" Value="AWSECommerceService"/>
   <Argument Name="Timestamp" Value="2017-02-28T19:39:59Z"/>
   <Argument Name="Version" Value="2013-08-01"/>
   <Argument Name="Signature" Value="fffZzJiCljfzaybcm0M9cIPX+kxi96U9LAMrF0+D5d4="/>
  </Arguments>
  <RequestProcessingTime>
   0.002379291
  </RequestProcessingTime>
 </OperationRequest>
 <BrowseNodes>
  <Request>
   <IsValid>
    True
   </IsValid>
   <BrowseNodeLookupRequest>
    <BrowseNodeId>
     13336081
    </BrowseNodeId>
   </BrowseNodeLookupRequest>
  </Request>
  <BrowseNode>
   <BrowseNodeId>
    13336081
   </BrowseNodeId>
   <Name>
    Paintings
   </Name>
   <Ancestors>
    <BrowseNode>
     <BrowseNodeId>
      3736081
     </BrowseNodeId>
     <Name>
      Wall Art
     </Name>
     <Ancestors>
      <BrowseNode>
       <BrowseNodeId>
        1063498
       </BrowseNodeId>
       <Name>
        Categories
       </Name>
       <IsCategoryRoot>
        1
       </IsCategoryRoot>
       <Ancestors>
        <BrowseNode>
         <BrowseNodeId>
          1055398
         </BrowseNodeId>
         <Name>
          Home &amp; Kitchen
         </Name>
        </BrowseNode>
       </Ancestors>
      </BrowseNode>
     </Ancestors>
    </BrowseNode>
   </Ancestors>
  </BrowseNode>
 </BrowseNodes>
</BrowseNodeLookupResponse>