<?xml version="1.0" encoding="utf-8"?>
<BrowseNodeLookupResponse xmlns="http://webservices.amazon.com/AWSECommerceService/2013-08-01">
 <OperationRequest>
  <HTTPHeaders>
   <Header Name="UserAgent" Value="Python-urllib/3.5"/>
  </HTTPHeaders>
  <RequestId>
   455cc618-16eb-412a-9d14-ecd72d5bd28b
  </RequestId>
  <Arguments>
   <Argument Name="AWSAccessKeyId" Value="AKIAJEGXYAPQ5DFQWHMA"/>
   <Argument Name="AssociateTag" Value="remaura-20"/>
   <Argument Name="BrowseNodeId" Value="367139011"/>
   <Argument Name="Operation" Value="BrowseNodeLookup"/>
   <Argument Name="Service" Value="AWSECommerceService"/>
   <Argument Name="Timestamp" Value="2017-02-28T19:03:36Z"/>
   <Argument Name="Version" Value="2013-08-01"/>
   <Argument Name="Signature" Value="MGu/hPfVSYw9Xu8HN/HtkKDVXMVhfZO+WX9tk3Vaxss="/>
  </Arguments>
  <RequestProcessingTime>
   0.001238107
  </RequestProcessingTime>
 </OperationRequest>
 <BrowseNodes>
  <Request>
   <IsValid>
    True
   </IsValid>
   <BrowseNodeLookupRequest>
    <BrowseNodeId>
     367139011
    </BrowseNodeId>
   </BrowseNodeLookupRequest>
  </Request>
  <BrowseNode>
   <BrowseNodeId>
    367139011
   </BrowseNodeId>
   <Name>
    Espresso Cups
   </Name>
   <Ancestors>
    <BrowseNode>
     <BrowseNodeId>
      367125011
     </BrowseNodeId>
     <Name>
      Cups, Mugs &amp; Saucers
     </Name>
     <Ancestors>
      <BrowseNode>
       <BrowseNodeId>
        13162311
       </BrowseNodeId>
       <Name>
        Dining &amp; Entertaining
       </Name>
       <Ancestors>
        <BrowseNode>
         <BrowseNodeId>
          284507
         </BrowseNodeId>
         <Name>
          Kitchen &amp; Dining
         </Name>
         <Ancestors>
          <BrowseNode>
           <BrowseNodeId>
            1063498
           </BrowseNodeId>
           <Name>
            Categories
           </Name>
           <IsCategoryRoot>
            1
           </IsCategoryRoot>
           <Ancestors>
            <BrowseNode>
             <BrowseNodeId>
              1055398
             </BrowseNodeId>
             <Name>
              Home &amp; Kitchen
             </Name>
            </BrowseNode>
           </Ancestors>
          </BrowseNode>
         </Ancestors>
        </BrowseNode>
       </Ancestors>
      </BrowseNode>
     </Ancestors>
    </BrowseNode>
   </Ancestors>
  </BrowseNode>
 </BrowseNodes>
</BrowseNodeLookupResponse>