<?xml version="1.0" ?><BrowseNodeLookupResponse xmlns="http://webservices.amazon.com/AWSECommerceService/2013-08-01"><OperationRequest><HTTPHeaders><Header Name="UserAgent" Value="Python-urllib/3.5"/></HTTPHeaders><RequestId>6c3b67f4-dce6-42a7-9cbf-ce350117c5e9</RequestId><Arguments><Argument Name="AWSAccessKeyId" Value="AKIAJEGXYAPQ5DFQWHMA"/><Argument Name="AssociateTag" Value="remaura-20"/><Argument Name="BrowseNodeId" Value="166836011"/><Argument Name="Operation" Value="BrowseNodeLookup"/><Argument Name="Service" Value="AWSECommerceService"/><Argument Name="Timestamp" Value="2017-02-28T00:09:19Z"/><Argument Name="Version" Value="2013-08-01"/><Argument Name="Signature" Value="EY2SkQ0X6l4I463pmGXIpOrflAw5LUyl1hWExFT2TP4="/></Arguments><RequestProcessingTime>0.002058906</RequestProcessingTime></OperationRequest><BrowseNodes><Request><IsValid>True</IsValid><BrowseNodeLookupRequest><BrowseNodeId>166836011</BrowseNodeId></BrowseNodeLookupRequest></Request><BrowseNode><BrowseNodeId>166836011</BrowseNodeId><Name>Accessories</Name><Children><BrowseNode><BrowseNodeId>8457328011</BrowseNodeId><Name>Adapters</Name></BrowseNode><BrowseNode><BrowseNodeId>8457330011</BrowseNodeId><Name>Automotive Seat Protector</Name></BrowseNode><BrowseNode><BrowseNodeId>2237488011</BrowseNodeId><Name>Bunting Bags</Name></BrowseNode><BrowseNode><BrowseNodeId>8457331011</BrowseNodeId><Name>Canopies &amp; Covers</Name></BrowseNode><BrowseNode><BrowseNodeId>8457333011</BrowseNodeId><Name>Chest &amp; Harness Clips</Name></BrowseNode><BrowseNode><BrowseNodeId>8457335011</BrowseNodeId><Name>Cushions</Name></BrowseNode><BrowseNode><BrowseNodeId>8457337011</BrowseNodeId><Name>Head &amp; Body Supports</Name></BrowseNode><BrowseNode><BrowseNodeId>2237472011</BrowseNodeId><Name>Rear Facing Mirrors</Name></BrowseNode><BrowseNode><BrowseNodeId>2237473011</BrowseNodeId><Name>Seat Back Kick Protectors</Name></BrowseNode><BrowseNode><BrowseNodeId>8457338011</BrowseNodeId><Name>Seat Liners</Name></BrowseNode><BrowseNode><BrowseNodeId>8457339011</BrowseNodeId><Name>Storage &amp; Organizers</Name></BrowseNode><BrowseNode><BrowseNodeId>8457340011</BrowseNodeId><Name>Strap &amp; Belt Covers</Name></BrowseNode><BrowseNode><BrowseNodeId>8457341011</BrowseNodeId><Name>Sun Protection</Name></BrowseNode><BrowseNode><BrowseNodeId>8457342011</BrowseNodeId><Name>Travel Bags &amp; Carts</Name></BrowseNode></Children><Ancestors><BrowseNode><BrowseNodeId>166835011</BrowseNodeId><Name>Car Seats &amp; Accessories</Name><Ancestors><BrowseNode><BrowseNodeId>165797011</BrowseNodeId><Name>Categories</Name><IsCategoryRoot>1</IsCategoryRoot><Ancestors><BrowseNode><BrowseNodeId>165796011</BrowseNodeId><Name>Baby Products</Name></BrowseNode></Ancestors></BrowseNode></Ancestors></BrowseNode></Ancestors></BrowseNode></BrowseNodes></BrowseNodeLookupResponse>