<?xml version="1.0" ?><BrowseNodeLookupResponse xmlns="http://webservices.amazon.com/AWSECommerceService/2013-08-01"><OperationRequest><HTTPHeaders><Header Name="UserAgent" Value="Python-urllib/3.5"/></HTTPHeaders><RequestId>9fc9bdc7-f208-4a4c-9756-92f03d9986f1</RequestId><Arguments><Argument Name="AWSAccessKeyId" Value="AKIAJEGXYAPQ5DFQWHMA"/><Argument Name="AssociateTag" Value="remaura-20"/><Argument Name="BrowseNodeId" Value="239226011"/><Argument Name="Operation" Value="BrowseNodeLookup"/><Argument Name="Service" Value="AWSECommerceService"/><Argument Name="Timestamp" Value="2017-02-28T00:12:32Z"/><Argument Name="Version" Value="2013-08-01"/><Argument Name="Signature" Value="UPkUZVw5Vx9GH3g/0T0x1vUA53skwVyiuQW+MfiX4Q4="/></Arguments><RequestProcessingTime>0.007449635</RequestProcessingTime></OperationRequest><BrowseNodes><Request><IsValid>True</IsValid><BrowseNodeLookupRequest><BrowseNodeId>239226011</BrowseNodeId></BrowseNodeLookupRequest></Request><BrowseNode><BrowseNodeId>239226011</BrowseNodeId><Name>Gifts</Name><Children><BrowseNode><BrowseNodeId>239231011</BrowseNodeId><Name>Albums, Frames &amp; Journals</Name></BrowseNode><BrowseNode><BrowseNodeId>394314011</BrowseNodeId><Name>Gift Baskets</Name></BrowseNode><BrowseNode><BrowseNodeId>239229011</BrowseNodeId><Name>Gift Sets</Name></BrowseNode><BrowseNode><BrowseNodeId>239228011</BrowseNodeId><Name>Keepsakes</Name></BrowseNode><BrowseNode><BrowseNodeId>196612011</BrowseNodeId><Name>Rattles</Name></BrowseNode><BrowseNode><BrowseNodeId>2237480011</BrowseNodeId><Name>Toy Banks</Name></BrowseNode></Children><Ancestors><BrowseNode><BrowseNodeId>165797011</BrowseNodeId><Name>Categories</Name><IsCategoryRoot>1</IsCategoryRoot><Ancestors><BrowseNode><BrowseNodeId>165796011</BrowseNodeId><Name>Baby Products</Name></BrowseNode></Ancestors></BrowseNode></Ancestors></BrowseNode></BrowseNodes></BrowseNodeLookupResponse>