<?xml version="1.0" ?><BrowseNodeLookupResponse xmlns="http://webservices.amazon.com/AWSECommerceService/2013-08-01"><OperationRequest><HTTPHeaders><Header Name="UserAgent" Value="Python-urllib/3.5"/></HTTPHeaders><RequestId>c2a0d14c-10fc-4b85-8557-d73264cb1515</RequestId><Arguments><Argument Name="AWSAccessKeyId" Value="AKIAJEGXYAPQ5DFQWHMA"/><Argument Name="AssociateTag" Value="remaura-20"/><Argument Name="BrowseNodeId" Value="16730"/><Argument Name="Operation" Value="BrowseNodeLookup"/><Argument Name="Service" Value="AWSECommerceService"/><Argument Name="Timestamp" Value="2017-02-28T03:47:19Z"/><Argument Name="Version" Value="2013-08-01"/><Argument Name="Signature" Value="DbhtQFt0bPoJXbvxcKOwmfItbxHJKnerYqjePC1bBy0="/></Arguments><RequestProcessingTime>0.002465002</RequestProcessingTime></OperationRequest><BrowseNodes><Request><IsValid>True</IsValid><BrowseNodeLookupRequest><BrowseNodeId>16730</BrowseNodeId></BrowseNodeLookupRequest></Request><BrowseNode><BrowseNodeId>16730</BrowseNodeId><Name>General</Name><Ancestors><BrowseNode><BrowseNodeId>16703</BrowseNodeId><Name>Africa</Name><Ancestors><BrowseNode><BrowseNodeId>27</BrowseNodeId><Name>Travel</Name><Ancestors><BrowseNode><BrowseNodeId>1000</BrowseNodeId><Name>Subjects</Name><IsCategoryRoot>1</IsCategoryRoot><Ancestors><BrowseNode><BrowseNodeId>283155</BrowseNodeId><Name>Books</Name></BrowseNode></Ancestors></BrowseNode></Ancestors></BrowseNode></Ancestors></BrowseNode></Ancestors></BrowseNode></BrowseNodes></BrowseNodeLookupResponse>