<?xml version="1.0" ?><BrowseNodeLookupResponse xmlns="http://webservices.amazon.com/AWSECommerceService/2013-08-01"><OperationRequest><HTTPHeaders><Header Name="UserAgent" Value="Python-urllib/3.5"/></HTTPHeaders><RequestId>827690fd-ff34-4c8b-8498-f3ed7dbcc5c4</RequestId><Arguments><Argument Name="AWSAccessKeyId" Value="AKIAJEGXYAPQ5DFQWHMA"/><Argument Name="AssociateTag" Value="remaura-20"/><Argument Name="BrowseNodeId" Value="290098"/><Argument Name="Operation" Value="BrowseNodeLookup"/><Argument Name="Service" Value="AWSECommerceService"/><Argument Name="Timestamp" Value="2017-02-28T03:29:23Z"/><Argument Name="Version" Value="2013-08-01"/><Argument Name="Signature" Value="W72jMnv5HKYlKiPUhM7QJUKGPZFf6RQt/AmhhNtAZc8="/></Arguments><RequestProcessingTime>0.007075224</RequestProcessingTime></OperationRequest><BrowseNodes><Request><IsValid>True</IsValid><BrowseNodeLookupRequest><BrowseNodeId>290098</BrowseNodeId></BrowseNodeLookupRequest></Request><BrowseNode><BrowseNodeId>290098</BrowseNodeId><Name>Trees</Name><Ancestors><BrowseNode><BrowseNodeId>290078</BrowseNodeId><Name>Field Guides</Name><Ancestors><BrowseNode><BrowseNodeId>26</BrowseNodeId><Name>Sports &amp; Outdoors</Name><Ancestors><BrowseNode><BrowseNodeId>1000</BrowseNodeId><Name>Subjects</Name><IsCategoryRoot>1</IsCategoryRoot><Ancestors><BrowseNode><BrowseNodeId>283155</BrowseNodeId><Name>Books</Name></BrowseNode></Ancestors></BrowseNode></Ancestors></BrowseNode></Ancestors></BrowseNode></Ancestors></BrowseNode></BrowseNodes></BrowseNodeLookupResponse>